pynlpir/__init__.py
pynlpir/cli.py
pynlpir/nlpir.py
pynlpir/pos_map.py
pynlpir/Data/BIG2GBK.map
pynlpir/Data/BIG5.pdat
pynlpir/Data/BIG5.wordlist
pynlpir/Data/BiWord.big
pynlpir/Data/Configure.xml
pynlpir/Data/CoreDict.pdat
pynlpir/Data/CoreDict.pos
pynlpir/Data/CoreDict.unig
pynlpir/Data/FTU8.pdat
pynlpir/Data/FTU8.wordlist
pynlpir/Data/FTU82GBK.map
pynlpir/Data/FieldDict.pdat
pynlpir/Data/FieldDict.pos
pynlpir/Data/GBK.pdat
pynlpir/Data/GBK.wordlist
pynlpir/Data/GBK2BIG.map
pynlpir/Data/GBK2FTU8.map
pynlpir/Data/GBK2GBKC.map
pynlpir/Data/GBK2UTF.map
pynlpir/Data/GBKA.pdat
pynlpir/Data/GBKA.wordlist
pynlpir/Data/GBKA2UTF.map
pynlpir/Data/GBKC.pdat
pynlpir/Data/GBKC.wordlist
pynlpir/Data/GBKC2GBK.map
pynlpir/Data/GranDict.pdat
pynlpir/Data/GranDict.pos
pynlpir/Data/ICTPOS.map
pynlpir/Data/KeyBlackList.pdat
pynlpir/Data/NLPIR.ctx
pynlpir/Data/NLPIR_First.map
pynlpir/Data/NewWord.lst
pynlpir/Data/PKU.map
pynlpir/Data/PKU_First.map
pynlpir/Data/UTF2GBK.map
pynlpir/Data/UTF2GBKA.map
pynlpir/Data/UTF8.pdat
pynlpir/Data/UTF8.wordlist
pynlpir/Data/UserDefinedDict.lst
pynlpir/Data/UserDict.pdat
pynlpir/Data/charset.type
pynlpir/Data/location.map
pynlpir/Data/location.pdat
pynlpir/Data/location.wordlist
pynlpir/Data/nr.ctx
pynlpir/Data/nr.fsa
pynlpir/Data/nr.role
pynlpir/Data/sentiment.pdat
pynlpir/Data/sentiment.ung
pynlpir/Data/English/English.pdat
pynlpir/Data/English/English.pos
pynlpir/Data/English/English.ung
pynlpir/Data/English/English.wordlist
pynlpir/Data/English/Irrel2regular.map
pynlpir/Data/English/ne.pdat
pynlpir/Data/English/ne.pos
pynlpir/Data/English/ne.wordlist
pynlpir/lib/NLPIR32.dll
pynlpir/lib/NLPIR32.lib
pynlpir/lib/NLPIR64.dll
pynlpir/lib/NLPIR64.lib
pynlpir/lib/libNLPIR32.so
pynlpir/lib/libNLPIR64.so
pynlpir/lib/libNLPIRios.so
pynlpir-0.6.1.dist-info/METADATA
pynlpir-0.6.1.dist-info/WHEEL
pynlpir-0.6.1.dist-info/entry_points.txt
pynlpir-0.6.1.dist-info/licenses/AUTHORS.rst
pynlpir-0.6.1.dist-info/licenses/LICENSE.txt
pynlpir-0.6.1.dist-info/RECORD
