Metadata-Version: 2.3
Name: PyNLPIR
Version: 0.6.1
Summary: A Python wrapper around the NLPIR/ICTCLAS Chinese segmentation software.
Project-URL: Documentation, https://tsroten.github.io/pynlpir
Project-URL: Changes, https://tsroten.github.io/pynlpir/history.html
Project-URL: Issue Tracker, https://github.com/tsroten/pynlpir/issues
Project-URL: Source Code, https://github.com/tsroten/pynlpir
Author: Thomas Roten
License: MIT
Keywords: chinese,ictclas,nlp,nlpir,pynlpir,segmentation
Classifier: Development Status :: 5 - Production/Stable
Classifier: Intended Audience :: Developers
Classifier: License :: OSI Approved :: MIT License
Classifier: Natural Language :: Chinese (Simplified)
Classifier: Natural Language :: Chinese (Traditional)
Classifier: Operating System :: MacOS :: MacOS X
Classifier: Operating System :: Microsoft :: Windows
Classifier: Operating System :: POSIX :: Linux
Classifier: Programming Language :: Python
Classifier: Programming Language :: Python :: 3
Classifier: Programming Language :: Python :: 3.9
Classifier: Programming Language :: Python :: 3.10
Classifier: Programming Language :: Python :: 3.11
Classifier: Programming Language :: Python :: 3.12
Classifier: Programming Language :: Python :: 3.13
Classifier: Topic :: Software Development :: Libraries :: Python Modules
Classifier: Topic :: Text Processing :: Linguistic
Requires-Python: >=3.9
Requires-Dist: click~=8.1
